torchsolver/__init__.py
torchsolver/config.py
torchsolver/module.py
torchsolver/solver.py
torchsolver/datasets/ImageFiles.py
torchsolver/datasets/__init__.py
torchsolver/losses/__init__.py
torchsolver/metrics/__init__.py
torchsolver/metrics/accuracy.py
torchsolver/models/__init__.py
torchsolver/nets/__init__.py
torchsolver/nets/dcgan.py
torchsolver/nets/gan.py
torchsolver/nn/__init__.py
torchsolver/nn/view.py
torchsolver/optimizers/__init__.py
torchsolver/schedulers/__init__.py
torchsolver/utils/__init__.py
torchsolver/utils/counter.py
torchsolver/utils/timer.py
torchsolver-1.5.1.dist-info/LICENSE
torchsolver-1.5.1.dist-info/METADATA
torchsolver-1.5.1.dist-info/WHEEL
torchsolver-1.5.1.dist-info/top_level.txt
torchsolver-1.5.1.dist-info/RECORD
