Metadata-Version: 2.1
Name: torchsolver
Version: 1.5.1
Summary: A pytorch based deep learning solver framework.
Home-page: https://github.com/killf/torchsolver
Author: killf
Author-email: killf@foxmail.com
License: UNKNOWN
Platform: UNKNOWN
Classifier: Programming Language :: Python :: 3
Classifier: License :: OSI Approved :: MIT License
Classifier: Operating System :: OS Independent
